codespaces_jupyterlab/__init__.py
codespaces_jupyterlab/_version.py
codespaces_jupyterlab/handlers.py
codespaces_jupyterlab/tests/__init__.py
codespaces_jupyterlab/tests/test_handlers.py
codespaces_jupyterlab-0.2.1.data/data/etc/jupyter/jupyter_notebook_config.d/codespaces_jupyterlab.json
codespaces_jupyterlab-0.2.1.data/data/etc/jupyter/jupyter_server_config.d/codespaces_jupyterlab.json
codespaces_jupyterlab-0.2.1.data/data/share/jupyter/labextensions/codespaces-jupyterlab/build_log.json
codespaces_jupyterlab-0.2.1.data/data/share/jupyter/labextensions/codespaces-jupyterlab/package.json
codespaces_jupyterlab-0.2.1.data/data/share/jupyter/labextensions/codespaces-jupyterlab/static/lib_index_js.d9fa1f15745fa589d9eb.js
codespaces_jupyterlab-0.2.1.data/data/share/jupyter/labextensions/codespaces-jupyterlab/static/lib_index_js.d9fa1f15745fa589d9eb.js.map
codespaces_jupyterlab-0.2.1.data/data/share/jupyter/labextensions/codespaces-jupyterlab/static/remoteEntry.34ae04ab4d7fb7237f20.js
codespaces_jupyterlab-0.2.1.data/data/share/jupyter/labextensions/codespaces-jupyterlab/static/remoteEntry.34ae04ab4d7fb7237f20.js.map
codespaces_jupyterlab-0.2.1.data/data/share/jupyter/labextensions/codespaces-jupyterlab/static/style.js
codespaces_jupyterlab-0.2.1.data/data/share/jupyter/labextensions/codespaces-jupyterlab/static/style_index_js.d4855198e2c0903784be.js
codespaces_jupyterlab-0.2.1.data/data/share/jupyter/labextensions/codespaces-jupyterlab/static/style_index_js.d4855198e2c0903784be.js.map
codespaces_jupyterlab-0.2.1.data/data/share/jupyter/labextensions/codespaces-jupyterlab/static/vendors-node_modules_css-loader_dist_runtime_api_js-node_modules_css-loader_dist_runtime_cssW-7d5e6f.22de5dab02cecb87ef7e.js
codespaces_jupyterlab-0.2.1.data/data/share/jupyter/labextensions/codespaces-jupyterlab/static/vendors-node_modules_css-loader_dist_runtime_api_js-node_modules_css-loader_dist_runtime_cssW-7d5e6f.22de5dab02cecb87ef7e.js.map
codespaces_jupyterlab-0.2.1.dist-info/METADATA
codespaces_jupyterlab-0.2.1.dist-info/WHEEL
codespaces_jupyterlab-0.2.1.dist-info/licenses/LICENSE
codespaces_jupyterlab-0.2.1.dist-info/RECORD
