Metadata-Version: 2.1
Name: codespaces_jupyterlab
Version: 0.2.1
Summary: A GitHub extension for codespaces in JupyterLab
Project-URL: Homepage, https://github.com/github/codespaces-jupyterlab
Project-URL: Bug Tracker, https://github.com/github/codespaces-jupyterlab/issues
Project-URL: Repository, https://github.com/github/codespaces-jupyterlab.git
Author-email: GitHub <me@test.com>
License: BSD 3-Clause License
License-File: LICENSE
Classifier: Framework :: Jupyter
Classifier: Framework :: Jupyter :: JupyterLab
Classifier: Framework :: Jupyter :: JupyterLab :: 3
Classifier: Framework :: Jupyter :: JupyterLab :: Extensions
Classifier: Framework :: Jupyter :: JupyterLab :: Extensions :: Prebuilt
Classifier: License :: OSI Approved :: BSD License
Classifier: Programming Language :: Python
Classifier: Programming Language :: Python :: 3
Classifier: Programming Language :: Python :: 3.7
Classifier: Programming Language :: Python :: 3.8
Classifier: Programming Language :: Python :: 3.9
Classifier: Programming Language :: Python :: 3.10
Classifier: Programming Language :: Python :: 3.11
Requires-Python: >=3.7
Requires-Dist: build
Requires-Dist: hatch
Requires-Dist: jupyter-server<3,>=1.6
Requires-Dist: maya>=0.6.1
Requires-Dist: twine
Provides-Extra: test
Requires-Dist: coverage; extra == 'test'
Requires-Dist: pytest; extra == 'test'
Requires-Dist: pytest-asyncio; extra == 'test'
Requires-Dist: pytest-cov; extra == 'test'
Requires-Dist: pytest-tornasync; extra == 'test'
